keyset_pagination/__init__.py
keyset_pagination/mixin.py
keyset_pagination/paginator.py
django_keyset_pagination_plus-0.9.9.dist-info/LICENSE
django_keyset_pagination_plus-0.9.9.dist-info/METADATA
django_keyset_pagination_plus-0.9.9.dist-info/WHEEL
django_keyset_pagination_plus-0.9.9.dist-info/top_level.txt
django_keyset_pagination_plus-0.9.9.dist-info/RECORD
