Metadata-Version: 2.1
Name: django-keyset-pagination-plus
Version: 0.9.9
Summary: Keyset Pagination (seek method) for django.
Home-page: https://bitbucket.org/schinckel/django-keyset-pagination
Author: Matthew Schinckel
Author-email: matt@schinckel.net
License: UNKNOWN
Platform: UNKNOWN
Classifier: Development Status :: 4 - Beta
Classifier: Framework :: Django
Classifier: Intended Audience :: Developers
Classifier: License :: OSI Approved :: BSD License
Classifier: Operating System :: OS Independent
Classifier: Programming Language :: Python :: 2.7
Classifier: Programming Language :: Python :: 3.6
Classifier: Programming Language :: Python :: 3.7
Classifier: Programming Language :: Python :: Implementation :: CPython
Classifier: Topic :: Software Development :: Libraries :: Python Modules
Requires-Python: >=2.7
Requires-Dist: django
